[
{
"id": 1,
"name": "Docker & Kubernetes Containerization",
"image": "https://images.unsplash.com/photo-1667372393119-3d4c48d07fc9?auto=format&fit=crop&w=800&q=80",
"rating": 4.9,
"students": 245,
"price": 55,
"level": "Intermediate",
"category": "DevOps",
"tags": ["Docker", "Kubernetes", "CI/CD", "Containers"],
"description": "Learn Docker, Kubernetes, container orchestration, deployment pipelines, scaling strategies, and cloud-native application deployment.",
"providerName": "Zayan Ahmed",
"providerEmail": "[zayan@skillswap.com](mailto:zayan@skillswap.com)",
"duration": "2 hours"
},
{
"id": 2,
"name": "TypeScript Enterprise Design Patterns",
"image": "https://images.unsplash.com/photo-1515879218367-8466d910aaa4?auto=format&fit=crop&w=800&q=80",
"rating": 4.8,
"students": 198,
"price": 40,
"level": "Advanced",
"category": "Frontend",
"tags": ["TypeScript", "Design Patterns", "React", "Architecture"],
"description": "Master advanced TypeScript concepts, design patterns, generics, decorators, and scalable frontend architecture.",
"providerName": "Sariha Kabir",
"providerEmail": "[sariha@skillswap.com](mailto:sariha@skillswap.com)",
"duration": "1.5 hours"
},
{
"id": 3,
"name": "PostgreSQL Database Performance Tuning",
"image": "https://images.unsplash.com/photo-1544383835-bda2bc66a55d?auto=format&fit=crop&w=800&q=80",
"rating": 4.7,
"students": 176,
"price": 48,
"level": "Intermediate",
"category": "Database",
"tags": ["PostgreSQL", "SQL", "Optimization", "Indexing"],
"description": "Improve query performance, optimize indexes, analyze execution plans, and manage large-scale PostgreSQL databases.",
"providerName": "Asif Nawaz",
"providerEmail": "[asif@skillswap.com](mailto:asif@skillswap.com)",
"duration": "2.5 hours"
},
{
"id": 4,
"name": "GraphQL API Architecture",
"image": "https://images.unsplash.com/photo-1555949963-aa79dcee981c?auto=format&fit=crop&w=800&q=80",
"rating": 4.9,
"students": 152,
"price": 60,
"level": "Advanced",
"category": "Backend",
"tags": ["GraphQL", "API", "Node.js", "Backend"],
"description": "Build scalable GraphQL APIs with schema design, resolvers, authentication, and performance optimization.",
"providerName": "Mariam Begum",
"providerEmail": "[mariam@skillswap.com](mailto:mariam@skillswap.com)",
"duration": "2 hours"
},
{
"id": 5,
"name": "Cyber Security & Ethical Hacking",
"image": "https://images.unsplash.com/photo-1563986768609-322da13575f3?auto=format&fit=crop&w=800&q=80",
"rating": 4.6,
"students": 267,
"price": 50,
"level": "Intermediate",
"category": "Security",
"tags": ["Cyber Security", "Pen Testing", "OWASP", "Ethical Hacking"],
"description": "Learn web security fundamentals, vulnerability assessment, OWASP Top 10, and ethical hacking techniques.",
"providerName": "Fahim Chowdhury",
"providerEmail": "[fahim@skillswap.com](mailto:fahim@skillswap.com)",
"duration": "3 hours"
},
{
"id": 6,
"name": "Product Management for Engineers",
"image": "https://images.unsplash.com/photo-1552664730-d307ca884978?auto=format&fit=crop&w=800&q=80",
"rating": 4.8,
"students": 138,
"price": 35,
"level": "Beginner",
"category": "Management",
"tags": ["Product Management", "Agile", "Scrum", "Leadership"],
"description": "Understand agile workflows, sprint planning, roadmap creation, stakeholder communication, and product strategy.",
"providerName": "Nuren Khan",
"providerEmail": "[nuren@skillswap.com](mailto:nuren@skillswap.com)",
"duration": "1 hour"
},
{
"id": 7,
"name": "Machine Learning with Python",
"image": "https://images.unsplash.com/photo-1527474305487-b87b222841cc?auto=format&fit=crop&w=800&q=80",
"rating": 4.9,
"students": 321,
"price": 65,
"level": "Intermediate",
"category": "AI & ML",
"tags": ["Python", "Machine Learning", "Scikit-Learn", "Data Science"],
"description": "Build machine learning models using Python, Scikit-Learn, feature engineering, and model evaluation techniques.",
"providerName": "Rafiul Islam",
"providerEmail": "[rafiul@skillswap.com](mailto:rafiul@skillswap.com)",
"duration": "3 hours"
},
{
"id": 8,
"name": "React & Next.js Full Stack Development",
"image": "https://images.unsplash.com/photo-1461749280684-dccba630e2f6?auto=format&fit=crop&w=800&q=80",
"rating": 4.8,
"students": 412,
"price": 58,
"level": "Intermediate",
"category": "Web Development",
"tags": ["React", "Next.js", "JavaScript", "Full Stack"],
"description": "Develop modern web applications with React, Next.js, routing, state management, and API integration.",
"providerName": "Tasnim Rahman",
"providerEmail": "[tasnim@skillswap.com](mailto:tasnim@skillswap.com)",
"duration": "2.5 hours"
},
{
"id": 9,
"name": "Mobile App Development with React Native",
"image": "https://images.unsplash.com/photo-1512941937669-90a1b58e7e9c?auto=format&fit=crop&w=800&q=80",
"rating": 4.7,
"students": 284,
"price": 52,
"level": "Intermediate",
"category": "Mobile Development",
"tags": ["React Native", "Mobile Apps", "Android", "iOS"],
"description": "Create cross-platform mobile apps using React Native, navigation, APIs, and mobile UI best practices.",
"providerName": "Shuvo Hasan",
"providerEmail": "[shuvo@skillswap.com](mailto:shuvo@skillswap.com)",
"duration": "2 hours"
},
{
"id": 10,
"name": "UI/UX Design Fundamentals",
"image": "https://images.unsplash.com/photo-1581291518857-4e27b48ff24e?auto=format&fit=crop&w=800&q=80",
"rating": 4.8,
"students": 350,
"price": 38,
"level": "Beginner",
"category": "Design",
"tags": ["UI Design", "UX Design", "Figma", "Prototyping"],
"description": "Learn user-centered design, wireframing, prototyping, design systems, and Figma workflow fundamentals.",
"providerName": "Nabila Akter",
"providerEmail": "[nabila@skillswap.com](mailto:nabila@skillswap.com)",
"duration": "1.5 hours"
}
]
